neptune_api/__init__.py
neptune_api/api/__init__.py
neptune_api/api/backend/__init__.py
neptune_api/api/backend/exchange_api_token.py
neptune_api/api/backend/get_client_config.py
neptune_api/api/backend/get_project.py
neptune_api/api/ingestion/__init__.py
neptune_api/api/ingestion/bulk_check_status.py
neptune_api/api/ingestion/check_details.py
neptune_api/api/ingestion/check_status.py
neptune_api/api/ingestion/ingest.py
neptune_api/api/retrieval/__init__.py
neptune_api/api/retrieval/get_attributes_with_paths_filter_proto.py
neptune_api/api/retrieval/get_multiple_float_series_values_proto.py
neptune_api/api/retrieval/get_series_values_proto.py
neptune_api/api/retrieval/get_timeseries_buckets_proto.py
neptune_api/api/retrieval/query_attribute_definitions_proto.py
neptune_api/api/retrieval/query_attribute_definitions_within_project.py
neptune_api/api/retrieval/query_attributes_within_project_proto.py
neptune_api/api/retrieval/search_global_leaderboard_entries_proto.py
neptune_api/api/retrieval/search_leaderboard_entries_proto.py
neptune_api/api/storage/__init__.py
neptune_api/api/storage/complete_multipart_upload.py
neptune_api/api/storage/signed_url.py
neptune_api/api/storage/signed_url_generic.py
neptune_api/auth_helpers.py
neptune_api/client.py
neptune_api/credentials.py
neptune_api/errors.py
neptune_api/models/__init__.py
neptune_api/models/api_error_type_dto.py
neptune_api/models/attribute_definition_dto.py
neptune_api/models/attribute_filter_dto.py
neptune_api/models/attribute_name_filter_dto.py
neptune_api/models/attribute_query_dto.py
neptune_api/models/attribute_type_dto.py
neptune_api/models/attributes_holder_identifier.py
neptune_api/models/client_config.py
neptune_api/models/client_versions_config_dto.py
neptune_api/models/complete_multipart_upload_request.py
neptune_api/models/create_signed_urls_request.py
neptune_api/models/create_signed_urls_response.py
neptune_api/models/error.py
neptune_api/models/file_to_sign.py
neptune_api-0.26.0.dist-info/METADATA
neptune_api-0.26.0.dist-info/WHEEL
neptune_api-0.26.0.dist-info/licenses/LICENSE
neptune_api-0.26.0.dist-info/RECORD
