Metadata-Version: 2.4
Name: neptune-api
Version: 0.26.0
Summary: A client library for accessing Neptune API
License: Apache-2.0
License-File: LICENSE
Keywords: MLOps,ML Experiment Tracking,ML Model Registry,ML Model Store,ML Metadata Store
Author: neptune.ai
Author-email: contact@neptune.ai
Requires-Python: >=3.8,<4.0
Classifier: Development Status :: 4 - Beta
Classifier: Environment :: Console
Classifier: Intended Audience :: Developers
Classifier: Intended Audience :: Science/Research
Classifier: License :: OSI Approved :: Apache Software License
Classifier: Natural Language :: English
Classifier: Operating System :: MacOS
Classifier: Operating System :: Microsoft :: Windows
Classifier: Operating System :: POSIX
Classifier: Operating System :: Unix
Classifier: Programming Language :: Python :: 3
Classifier: Programming Language :: Python :: 3.8
Classifier: Programming Language :: Python :: 3.9
Classifier: Programming Language :: Python :: 3.10
Classifier: Programming Language :: Python :: 3.11
Classifier: Programming Language :: Python :: 3.12
Classifier: Programming Language :: Python :: 3.13
Classifier: Programming Language :: Python :: 3.14
Classifier: Topic :: Scientific/Engineering :: Artificial Intelligence
Classifier: Topic :: Software Development :: Libraries :: Python Modules
Requires-Dist: PyJWT (>=2.0.0,<3.0.0)
Requires-Dist: attrs (>=21.3.0)
Requires-Dist: httpx[http2] (>=0.15.4,<0.28.2)
Requires-Dist: protobuf (>=4.21.1,<7)
Requires-Dist: python-dateutil (>=2.8.0,<3.0.0)
Project-URL: Documentation, https://docs.neptune.ai/
Project-URL: Repository, https://github.com/neptune-ai/neptune-api
Project-URL: Tracker, https://github.com/neptune-ai/neptune-api/issues
